adafruit_ble_berrymed_pulse_oximeter/__init__.py
adafruit_ble_berrymed_pulse_oximeter/adafruit_ble_transparent_uart.py
adafruit_circuitpython_ble_berrymed_pulse_oximeter-2.0.22.dist-info/licenses/LICENSE
adafruit_circuitpython_ble_berrymed_pulse_oximeter-2.0.22.dist-info/METADATA
adafruit_circuitpython_ble_berrymed_pulse_oximeter-2.0.22.dist-info/WHEEL
adafruit_circuitpython_ble_berrymed_pulse_oximeter-2.0.22.dist-info/top_level.txt
adafruit_circuitpython_ble_berrymed_pulse_oximeter-2.0.22.dist-info/RECORD
