Metadata-Version: 2.4
Name: adafruit-circuitpython-ble-berrymed-pulse-oximeter
Version: 2.0.22
Summary: BLE Support for BerryMed Pulse Oximeter Service
Author-email: Adafruit Industries <circuitpython@adafruit.com>
License: MIT
Project-URL: Homepage, https://github.com/adafruit/Adafruit_CircuitPython_BLE_BerryMed_Pulse_Oximeter
Keywords: adafruit,blinka,circuitpython,micropython,ble_berrymed_pulse_oximeter,ble,pulse,oximeter,berrymed,spo2
Classifier: Intended Audience :: Developers
Classifier: Topic :: Software Development :: Libraries
Classifier: Topic :: Software Development :: Embedded Systems
Classifier: Topic :: System :: Hardware
Classifier: License :: OSI Approved :: MIT License
Classifier: Programming Language :: Python :: 3
License-File: LICENSE
Requires-Dist: Adafruit-Blinka>=7.2.3
Requires-Dist: adafruit-circuitpython-ble
Provides-Extra: optional
Dynamic: license-file
